tweakreg_hack/__init__.py
tweakreg_hack/catalogs.py
tweakreg_hack/imgclasses.py
tweakreg_hack/tweakreg.py
tweakreg_hack/tweakreg_step_hack.py
tweakreg_hack/tweakreg_step_old.py
tweakreg_hack/tweakutils.py
tweakreg_hack/util.py
tweakreg_hack-0.1.1.dist-info/METADATA
tweakreg_hack-0.1.1.dist-info/WHEEL
tweakreg_hack-0.1.1.dist-info/top_level.txt
tweakreg_hack-0.1.1.dist-info/RECORD
