Metadata-Version: 2.1
Name: tweakreg_hack
Version: 0.1.1
Author: Justin Pierel
Author-email: jpierel@stsci.edu
License: BSD
Requires-Dist: numpy
Requires-Dist: astropy
Requires-Dist: jwst
